eventextraction/__init__.py
eventextraction/etx.py
eventextraction-1.1.dist-info/LICENSE
eventextraction-1.1.dist-info/METADATA
eventextraction-1.1.dist-info/WHEEL
eventextraction-1.1.dist-info/top_level.txt
eventextraction-1.1.dist-info/RECORD
