Metadata-Version: 2.1
Name: eventextraction
Version: 1.1
Summary: 中文复合事件抽取，可以用来识别文本的模式，包括条件事件、因果事件、顺承事件、反转事件。代码为刘焕勇原创设计,项目地址https://github.com/liuhuanyong/ComplexEventExtraction 项目介绍很详细，感兴趣的一定要去原项目看一下。我仅仅是对代码做了简单的修改，增加了函数说明注释和stats函数，可以用于统计文本中各种模式的分布(数量)情况。
Home-page: https://github.com/hidadeng/eventextraction
Author: 大邓
Author-email: thunderhit@qq.com
License: MIT
Keywords: knowledge graph,text analysis,event extraction
Platform: UNKNOWN
Requires-Python: >=3.5
